odoo/addons/pos_cashier_login/README.rst
odoo/addons/pos_cashier_login/__init__.py
odoo/addons/pos_cashier_login/__manifest__.py
odoo/addons/pos_cashier_login/i18n/ca.po
odoo/addons/pos_cashier_login/i18n/es.po
odoo/addons/pos_cashier_login/i18n/pos_cashier_login.pot
odoo/addons/pos_cashier_login/models/__init__.py
odoo/addons/pos_cashier_login/models/pos_config.py
odoo/addons/pos_cashier_login/readme/CONTRIBUTORS.rst
odoo/addons/pos_cashier_login/readme/DESCRIPTION.rst
odoo/addons/pos_cashier_login/readme/USAGE.rst
odoo/addons/pos_cashier_login/static/description/icon.png
odoo/addons/pos_cashier_login/static/description/index.html
odoo/addons/pos_cashier_login/static/src/css/main.css
odoo/addons/pos_cashier_login/static/src/js/main.js
odoo/addons/pos_cashier_login/static/src/xml/main.xml
odoo/addons/pos_cashier_login/views/assets.xml
odoo/addons/pos_cashier_login/views/pos_config.xml
odoo11_addon_pos_cashier_login-11.0.0.1.2.dist-info/METADATA
odoo11_addon_pos_cashier_login-11.0.0.1.2.dist-info/WHEEL
odoo11_addon_pos_cashier_login-11.0.0.1.2.dist-info/top_level.txt
odoo11_addon_pos_cashier_login-11.0.0.1.2.dist-info/RECORD
